throwaway_keys/__init__.py
throwaway_keys/__main__.py
throwaway_keys-0.0.8.dist-info/LICENSE
throwaway_keys-0.0.8.dist-info/METADATA
throwaway_keys-0.0.8.dist-info/WHEEL
throwaway_keys-0.0.8.dist-info/top_level.txt
throwaway_keys-0.0.8.dist-info/RECORD
