Metadata-Version: 2.1
Name: throwaway-keys
Version: 0.0.8
Summary: Package to generate 'throwaway keys' for encrypting information
Home-page: https://github.com/ii-Python/throwaway-keys
Author: iiPython
Author-email: ben@iipython.cf
License: UNKNOWN
Keywords: keys,sha256,encryption,hashlib
Platform: UNKNOWN
Classifier: Programming Language :: Python :: 3.9
Classifier: License :: OSI Approved :: MIT License
Classifier: Operating System :: Microsoft :: Windows
Classifier: Operating System :: POSIX
Classifier: Intended Audience :: Developers
Classifier: Intended Audience :: System Administrators
Classifier: Environment :: Console
Classifier: Development Status :: 2 - Pre-Alpha
Classifier: Natural Language :: English
Classifier: Topic :: Security :: Cryptography
Requires-Python: >=3.6.2
